autotagger/__init__.py
autotagger/admin.py
autotagger/autotag_content.py
autotagger/how_to.md
autotagger/models.py
tango_autotagger-0.3.0.dist-info/METADATA
tango_autotagger-0.3.0.dist-info/RECORD
tango_autotagger-0.3.0.dist-info/WHEEL
tango_autotagger-0.3.0.dist-info/top_level.txt
