Metadata-Version: 2.1
Name: tango-autotagger
Version: 0.3.0
Summary: 
Home-page: http://github.com/tBaxter/autotagger
Author: Tim Baxter
Author-email: mail.baxter@gmail.com
License: LICENSE
Platform: UNKNOWN
